git_timemachine/__about__.py
git_timemachine/__init__.py
git_timemachine/__main__.py
git_timemachine/git.py
git_timemachine/models.py
git_timemachine/commands/__init__.py
git_timemachine/commands/advance.py
git_timemachine/commands/commit.py
git_timemachine/commands/review.py
git_timemachine-2.2.1.dist-info/METADATA
git_timemachine-2.2.1.dist-info/WHEEL
git_timemachine-2.2.1.dist-info/entry_points.txt
git_timemachine-2.2.1.dist-info/licenses/LICENSE
git_timemachine-2.2.1.dist-info/RECORD
