Metadata-Version: 2.4
Name: git-timemachine
Version: 2.2.1
Summary: A command-line tool that helps you record commits on Git repositories at any time node.
Project-URL: homepage, https://github.com/garrett-he/git-timemachine
Project-URL: repository, https://github.com/garrett-he/git-timemachine.git
Project-URL: changelog, https://github.com/garrett-he/git-timemachine/blob/main/CHANGELOG.md
Author-email: Garrett HE <garrett.he@outlook.com>
License: BSD-3-Clause
License-File: LICENSE
Keywords: committing,git,timemachine
Classifier: Development Status :: 2 - Pre-Alpha
Classifier: Programming Language :: Python :: 3
Classifier: Programming Language :: Python :: 3.12
Classifier: Programming Language :: Python :: 3.13
Requires-Python: >=3.12
Requires-Dist: prettytable>=3.16.0
Requires-Dist: pydantic>=2.11.9
Requires-Dist: pygit2>=1.18.2
Requires-Dist: requests>=2.32.5
Requires-Dist: typer>=0.16.1
